Metadata-Version: 1.0
Name: dsnddistributions
Version: 0.1
Summary: Gaussian and Binomial distributions
Home-page: UNKNOWN
Author: Leonard Nwobodo
Author-email: alphamale.july@gmail.com
License: UNKNOWN
Platform: UNKNOWN
